xontrib/enhancd.py
xontrib/enhancd_lib/__init__.py
xontrib/enhancd_lib/cd.py
xontrib/enhancd_lib/filepath.py
xontrib/enhancd_lib/filter.py
xontrib/enhancd_lib/history.py
xontrib/enhancd_lib/sources.py
xontrib/enhancd_lib/variable.py
xontrib_enhancd-0.1.0.dist-info/LICENSE
xontrib_enhancd-0.1.0.dist-info/METADATA
xontrib_enhancd-0.1.0.dist-info/WHEEL
xontrib_enhancd-0.1.0.dist-info/top_level.txt
xontrib_enhancd-0.1.0.dist-info/RECORD
