Metadata-Version: 2.1
Name: xontrib-enhancd
Version: 0.1.0
Summary: b4b4r07/enhancd for xonsh
Home-page: https://github.com/sun-yryr/xontrib-enhancd
Author: sun-yryr
Author-email: taittide@gmail.com
License: MIT
Platform: any
Classifier: Programming Language :: Python :: 3
Classifier: Programming Language :: Python :: 3.5
Classifier: Programming Language :: Python :: 3.6
Classifier: Programming Language :: Python :: 3.7
Classifier: Programming Language :: Python :: 3.8
Classifier: License :: OSI Approved :: MIT License
Requires-Python: >=3.5
Requires-Dist: xonsh
Requires-Dist: fuzzysearch
